[
  {
    "logo": "./assets/images/logo-devlens.svg",
    "id": 1,
    "name": "DevLens",
    "description": "Quickly inspect page layouts and visualize element boundaries.",
    "isActive": true
  },
  {
    "logo": "./assets/images/logo-style-spy.svg",
    "id": 2,
    "name": "StyleSpy",
    "description": "Instantly analyze and copy CSS from any webpage element.",
    "isActive": true
  },
  {
    "logo": "./assets/images/logo-speed-boost.svg",
    "id": 3,
    "name": "SpeedBoost",
    "description": "Optimizes browser resource usage to accelerate page loading.",
    "isActive": false
  },
  {
    "logo": "./assets/images/logo-json-wizard.svg",
    "id": 4,
    "name": "JSONWizard",
    "description": "Formats, validates, and prettifies JSON responses in-browser.",
    "isActive": true
  },
  {
    "logo": "./assets/images/logo-tab-master-pro.svg",
    "id": 5,
    "name": "TabMaster Pro",
    "description": "Organizes browser tabs into groups and sessions.",
    "isActive": true
  },
  {
    "logo": "./assets/images/logo-viewport-buddy.svg",
    "id": 6,
    "name": "ViewportBuddy",
    "description": "Simulates various screen resolutions directly within the browser.",
    "isActive": false
  },
  {
    "logo": "./assets/images/logo-markup-notes.svg",
    "id": 7,
    "name": "Markup Notes",
    "description": "Enables annotation and notes directly onto webpages for collaborative debugging.",
    "isActive": true
  },
  {
    "logo": "./assets/images/logo-grid-guides.svg",
    "id": 8,
    "name": "GridGuides",
    "description": "Overlay customizable grids and alignment guides on any webpage.",
    "isActive": false
  },
  {
    "logo": "./assets/images/logo-palette-picker.svg",
    "id": 9,
    "name": "Palette Picker",
    "description": "Instantly extracts color palettes from any webpage.",
    "isActive": true
  },
  {
    "logo": "./assets/images/logo-link-checker.svg",
    "id": 10,
    "name": "LinkChecker",
    "description": "Scans and highlights broken links on any page.",
    "isActive": true
  },
  {
    "logo": "./assets/images/logo-dom-snapshot.svg",
    "id": 11,
    "name": "DOM Snapshot",
    "description": "Capture and export DOM structures quickly.",
    "isActive": false
  },
  {
    "logo": "./assets/images/logo-console-plus.svg",
    "id": 12,
    "name": "ConsolePlus",
    "description": "Enhanced developer console with advanced filtering and logging.",
    "isActive": true
  }
]
